bs_roformer/__init__.py
bs_roformer/__main__.py
bs_roformer/attend.py
bs_roformer/bs_roformer.py
bs_roformer/config_bs_roformer_384_8_2_485100.yaml
bs_roformer/inference.py
bs_roformer/mel_band_roformer.py
bs_roformer/utils.py
Lossless_BS_RoFormer-1.0.0.dist-info/LICENSE
Lossless_BS_RoFormer-1.0.0.dist-info/METADATA
Lossless_BS_RoFormer-1.0.0.dist-info/WHEEL
Lossless_BS_RoFormer-1.0.0.dist-info/top_level.txt
Lossless_BS_RoFormer-1.0.0.dist-info/RECORD
